MANIFEST.in
setup.py
anthill/social/__init__.py
anthill/social/admin.py
anthill/social/handler.py
anthill/social/options.py
anthill/social/server.py
anthill/social/model/__init__.py
anthill/social/model/connection.py
anthill/social/model/group.py
anthill/social/model/names.py
anthill/social/model/profile.py
anthill/social/model/request.py
anthill/social/model/token.py
anthill/social/model/social/__init__.py
anthill/social/model/social/facebook.py
anthill/social/model/social/google.py
anthill/social/model/social/mailru.py
anthill/social/model/social/steam.py
anthill/social/model/social/vk.py
anthill/social/sql/account_connections.sql
anthill/social/sql/credential_tokens.sql
anthill/social/sql/group_participants.sql
anthill/social/sql/groups.sql
anthill/social/sql/requests.sql
anthill/social/sql/requests_expiration.sql
anthill/social/sql/unique_names.sql
anthill/social/tests/__init__.py
anthill/social/tests/test_groups.py
anthill_social.egg-info/PKG-INFO
anthill_social.egg-info/SOURCES.txt
anthill_social.egg-info/dependency_links.txt
anthill_social.egg-info/namespace_packages.txt
anthill_social.egg-info/not-zip-safe
anthill_social.egg-info/requires.txt
anthill_social.egg-info/top_level.txt