Metadata-Version: 1.0
Name: anthill-social
Version: 0.2
Summary: Social service for Anthill platform
Home-page: https://github.com/anthill-platform/anthill-social
Author: desertkun
Author-email: desertkun@gmail.com
License: MIT
Platform: UNKNOWN
